__init__.py
parallelprocs.py
parallelprocs-0.1.4.dist-info/LICENSE
parallelprocs-0.1.4.dist-info/METADATA
parallelprocs-0.1.4.dist-info/WHEEL
parallelprocs-0.1.4.dist-info/top_level.txt
parallelprocs-0.1.4.dist-info/RECORD
