Metadata-Version: 2.1
Name: parallelprocs
Version: 0.1.4
Summary: Run command lines via (GNU) parallel
Home-page: https://github.com/kyclark/parallelprocs
Author: Ken Youens-Clark
Author-email: kyclark@gmail.com
License: UNKNOWN
Platform: UNKNOWN
Classifier: Programming Language :: Python :: 3
Classifier: License :: OSI Approved :: MIT License
Classifier: Operating System :: OS Independent
